keras_hub/__init__.py
keras_hub/layers/__init__.py
keras_hub/metrics/__init__.py
keras_hub/models/__init__.py
keras_hub/samplers/__init__.py
keras_hub/src/__init__.py
keras_hub/src/api_export.py
keras_hub/src/version.py
keras_hub/src/layers/__init__.py
keras_hub/src/layers/modeling/__init__.py
keras_hub/src/layers/modeling/alibi_bias.py
keras_hub/src/layers/modeling/anchor_generator.py
keras_hub/src/layers/modeling/box_matcher.py
keras_hub/src/layers/modeling/cached_multi_head_attention.py
keras_hub/src/layers/modeling/f_net_encoder.py
keras_hub/src/layers/modeling/masked_lm_head.py
keras_hub/src/layers/modeling/non_max_supression.py
keras_hub/src/layers/modeling/position_embedding.py
keras_hub/src/layers/modeling/reversible_embedding.py
keras_hub/src/layers/modeling/rms_normalization.py
keras_hub/src/layers/modeling/rotary_embedding.py
keras_hub/src/layers/modeling/sine_position_encoding.py
keras_hub/src/layers/modeling/token_and_position_embedding.py
keras_hub/src/layers/modeling/transformer_decoder.py
keras_hub/src/layers/modeling/transformer_encoder.py
keras_hub/src/layers/modeling/transformer_layer_utils.py
keras_hub/src/layers/preprocessing/__init__.py
keras_hub/src/layers/preprocessing/audio_converter.py
keras_hub/src/layers/preprocessing/image_converter.py
keras_hub/src/layers/preprocessing/masked_lm_mask_generator.py
keras_hub/src/layers/preprocessing/multi_segment_packer.py
keras_hub/src/layers/preprocessing/preprocessing_layer.py
keras_hub/src/layers/preprocessing/random_deletion.py
keras_hub/src/layers/preprocessing/random_swap.py
keras_hub/src/layers/preprocessing/start_end_packer.py
keras_hub/src/metrics/__init__.py
keras_hub/src/metrics/bleu.py
keras_hub/src/metrics/edit_distance.py
keras_hub/src/metrics/perplexity.py
keras_hub/src/metrics/rouge_base.py
keras_hub/src/metrics/rouge_l.py
keras_hub/src/metrics/rouge_n.py
keras_hub/src/models/__init__.py
keras_hub/src/models/audio_to_text.py
keras_hub/src/models/audio_to_text_preprocessor.py
keras_hub-0.25.0.dist-info/METADATA
keras_hub-0.25.0.dist-info/WHEEL
keras_hub-0.25.0.dist-info/top_level.txt
keras_hub-0.25.0.dist-info/RECORD
