Metadata-Version: 2.4
Name: keras-hub
Version: 0.25.0
Summary: Pretrained models for Keras.
Author-email: Keras team <keras-users@googlegroups.com>
License-Expression: Apache-2.0
Project-URL: Home, https://keras.io/keras_hub/
Project-URL: Repository, https://github.com/keras-team/keras/keras_hub
Classifier: Development Status :: 3 - Alpha
Classifier: Programming Language :: Python :: 3
Classifier: Programming Language :: Python :: 3.9
Classifier: Programming Language :: Python :: 3.10
Classifier: Programming Language :: Python :: 3.11
Classifier: Programming Language :: Python :: 3 :: Only
Classifier: Operating System :: Unix
Classifier: Operating System :: Microsoft :: Windows
Classifier: Operating System :: MacOS
Classifier: Intended Audience :: Science/Research
Classifier: Topic :: Scientific/Engineering
Classifier: Topic :: Software Development
Requires-Python: >=3.10
Requires-Dist: keras>=3.8
Requires-Dist: absl-py
Requires-Dist: numpy
Requires-Dist: packaging
Requires-Dist: regex
Requires-Dist: rich
Requires-Dist: kagglehub
Requires-Dist: tensorflow-text; platform_system != "Windows"
